axon/__init__.py
axon/config.py
axon/core.py
axon/models.py
ax0n_ai-0.1.0.dist-info/METADATA
ax0n_ai-0.1.0.dist-info/WHEEL
ax0n_ai-0.1.0.dist-info/licenses/LICENSE
ax0n_ai-0.1.0.dist-info/RECORD
