Metadata-Version: 2.4
Name: ax0n-ai
Version: 0.1.0
Summary: Model-agnostic Think & Memory layer for LLMs
Project-URL: Homepage, https://github.com/axon-ai/axon
Project-URL: Documentation, https://axon.readthedocs.io
Project-URL: Repository, https://github.com/axon-ai/axon.git
Project-URL: Bug Tracker, https://github.com/axon-ai/axon/issues
Author-email: Ax0n Team <install.py@gmail.com>
License: MIT
License-File: LICENSE
Keywords: ai,grounding,llm,memory,reasoning
Classifier: Development Status :: 3 - Alpha
Classifier: Intended Audience :: Developers
Classifier: License :: OSI Approved :: MIT License
Classifier: Programming Language :: Python :: 3
Classifier: Programming Language :: Python :: 3.8
Classifier: Programming Language :: Python :: 3.9
Classifier: Programming Language :: Python :: 3.10
Classifier: Programming Language :: Python :: 3.11
Classifier: Programming Language :: Python :: 3.12
Classifier: Topic :: Scientific/Engineering :: Artificial Intelligence
Requires-Python: >=3.8
Requires-Dist: aiohttp>=3.8.0
Requires-Dist: anthropic>=0.7.0
Requires-Dist: asyncio-mqtt>=0.11.0
Requires-Dist: beautifulsoup4>=4.11.0
Requires-Dist: lxml>=4.9.0
Requires-Dist: numpy>=1.21.0
Requires-Dist: openai>=1.0.0
Requires-Dist: pinecone-client>=2.2.0
Requires-Dist: pydantic>=2.0.0
Requires-Dist: python-dotenv>=1.0.0
Requires-Dist: redis>=4.5.0
Requires-Dist: requests>=2.28.0
Requires-Dist: structlog>=23.0.0
Requires-Dist: tenacity>=8.2.0
Requires-Dist: weaviate-client>=3.25.0
Provides-Extra: dev
Requires-Dist: black>=23.0.0; extra == 'dev'
Requires-Dist: flake8>=6.0.0; extra == 'dev'
Requires-Dist: isort>=5.12.0; extra == 'dev'
Requires-Dist: mypy>=1.0.0; extra == 'dev'
Requires-Dist: pre-commit>=3.0.0; extra == 'dev'
Requires-Dist: pytest-asyncio>=0.21.0; extra == 'dev'
Requires-Dist: pytest-cov>=4.0.0; extra == 'dev'
Requires-Dist: pytest>=7.0.0; extra == 'dev'
Provides-Extra: docs
Requires-Dist: mkdocs-material>=9.0.0; extra == 'docs'
Requires-Dist: mkdocs>=1.4.0; extra == 'docs'
Requires-Dist: mkdocstrings[python]>=0.20.0; extra == 'docs'
